kenallclient/__init__.py
kenallclient/__main__.py
kenallclient/client.py
kenallclient/model.py
kenallclient/types.py
kenallclient/models/__init__.py
kenallclient/models/compatible.py
kenallclient/models/factories.py
kenallclient/models/v20221101.py
kenallclient/models/v20230901.py
kenallclient/models/v20240101.py
kenallclient/models/v20250101.py
kenallclient-1.1.0.dist-info/licenses/LICENSE
kenallclient-1.1.0.dist-info/METADATA
kenallclient-1.1.0.dist-info/WHEEL
kenallclient-1.1.0.dist-info/top_level.txt
kenallclient-1.1.0.dist-info/RECORD
