Metadata-Version: 2.4
Name: kenallclient
Version: 1.1.0
Summary: simple client for kenall.jp API service.
Author-email: Atsushi Odagiri <aodagx@gmail.com>
License: MIT
Project-URL: Homepage, https://github.com/ken-all/python-kenallclient
License-File: LICENSE
Requires-Dist: dataclasses; python_version <= "3.6"
Provides-Extra: testing
Requires-Dist: pytest; extra == "testing"
Requires-Dist: pytest-cov; extra == "testing"
Requires-Dist: pytest-randomly; extra == "testing"
Requires-Dist: pytest-mock; extra == "testing"
Provides-Extra: dev
Requires-Dist: ruff; extra == "dev"
Requires-Dist: mypy; extra == "dev"
Provides-Extra: release
Requires-Dist: nox; extra == "release"
Requires-Dist: build; extra == "release"
Requires-Dist: twine; extra == "release"
Dynamic: license-file
